equilipy/ScheilCooling.py
equilipy/InputCondition.py
equilipy/ListPhases.py
equilipy/PhaseSelection.py
equilipy/ParseCSDataBlockRKMP.py
equilipy/variables.py
equilipy/PostProcess.py
equilipy/ParseCSDataBlockGibbs.py
equilipy/__init__.py
equilipy/Minimize.py
equilipy/ParseCSDataBlockQKTO.py
equilipy/InternalFunctions.py
equilipy/SystemCheck.py
equilipy/ParseCSHeader.py
equilipy/ParseCSDataBlockSUBG.py
equilipy/ReadDict.py
equilipy/ParseCSDataBlock.py
equilipy/Simplex.py
equilipy/Errors.py
equilipy/ReadDAT.py
equilipy/equilifort.cpython-39-darwin.so
equilipy/EquilibSingle.py
equilipy/EquilibBatch.py
equilipy/ParseCSDataBlockSUBL.py
equilipy/.dylibs/libgfortran.5.dylib
equilipy/.dylibs/libquadmath.0.dylib
equilipy/.dylibs/libgcc_s.1.1.dylib
equilipy_hpc-0.1.3.dist-info/RECORD
equilipy_hpc-0.1.3.dist-info/WHEEL
equilipy_hpc-0.1.3.dist-info/entry_points.txt
equilipy_hpc-0.1.3.dist-info/top_level.txt
equilipy_hpc-0.1.3.dist-info/METADATA
