Metadata-Version: 2.1
Name: equilipy-hpc
Version: 0.1.3
Author: Sunyong Kwon
Author-email: sunyong.kwon@mail.mcgill.ca
License: BSD-3
Requires-Python: >=3.9
Requires-Dist: numpy
Requires-Dist: glob2
Requires-Dist: regex
Requires-Dist: numba
Requires-Dist: dataclasses
Requires-Dist: meson
Requires-Dist: ninja
Requires-Dist: polars
Requires-Dist: xlsx2csv
Requires-Dist: matplotlib
Requires-Dist: tqdm
Requires-Dist: mpi4py
